Metadata-Version: 1.0
Name: mr-distributions
Version: 0.1
Summary: Gaussian and Binomial distributions
Home-page: UNKNOWN
Author: Prasil Adhikari
Author-email: adhikariprasil7@gmail.com
License: UNKNOWN
Platform: UNKNOWN
